colorful/__init__.py
colorful/fields.py
colorful/forms.py
colorful/models.py
colorful/widgets.py
colorful/static/colorful/arrow.gif
colorful/static/colorful/colorPicker.css
colorful/static/colorful/jQuery.colorPicker.js
django_colorful_scybear-1.2.1.dist-info/LICENSE.txt
django_colorful_scybear-1.2.1.dist-info/METADATA
django_colorful_scybear-1.2.1.dist-info/RECORD
django_colorful_scybear-1.2.1.dist-info/WHEEL
django_colorful_scybear-1.2.1.dist-info/top_level.txt
